LICENSE
MANIFEST.in
README.md
package.json
setup.py
dash_renderjson/DashRenderjson.py
dash_renderjson/__init__.py
dash_renderjson/_imports_.py
dash_renderjson/dash_renderjson.min.js
dash_renderjson/dash_renderjson.min.js.map
dash_renderjson/metadata.json
dash_renderjson/package-info.json
dash_renderjson.egg-info/PKG-INFO
dash_renderjson.egg-info/SOURCES.txt
dash_renderjson.egg-info/dependency_links.txt
dash_renderjson.egg-info/top_level.txt