Metadata-Version: 1.1
Name: dash-renderjson
Version: 0.0.1
Summary: Render dicts/json files with Dash
Home-page: UNKNOWN
Author: Andy Challis <andrewchallis@hotmail.co.uk>
Author-email: UNKNOWN
License: MIT
Platform: UNKNOWN
Classifier: Framework :: Dash
